odoo_rpc_client_cli/__init__.py
odoo_rpc_client_cli/cli.py
odoo_rpc_client_cli/db.py
odoo_rpc_client_cli-0.1.0.dist-info/DESCRIPTION.rst
odoo_rpc_client_cli-0.1.0.dist-info/METADATA
odoo_rpc_client_cli-0.1.0.dist-info/RECORD
odoo_rpc_client_cli-0.1.0.dist-info/WHEEL
odoo_rpc_client_cli-0.1.0.dist-info/entry_points.txt
odoo_rpc_client_cli-0.1.0.dist-info/metadata.json
odoo_rpc_client_cli-0.1.0.dist-info/top_level.txt
