Metadata-Version: 2.0
Name: odoo-rpc-client-cli
Version: 0.1.0
Summary: CLI for odoo-rpc-client project
Home-page: https://github.com/katyukha/odoo-rpc-client-cli
Author: Dmytro Katyukha
Author-email: firemage.dima@gmail.com
License: GPL
Platform: any
Classifier: Development Status :: 3 - Alpha
Classifier: Environment :: Console
Classifier: Intended Audience :: Developers
Classifier: License :: OSI Approved :: GNU General Public License (GPL)
Classifier: Operating System :: POSIX
Classifier: Operating System :: MacOS
Classifier: Operating System :: Unix
Classifier: Programming Language :: Python
Classifier: Programming Language :: Python :: 2
Classifier: Programming Language :: Python :: 3
Classifier: Topic :: Software Development :: Libraries :: Python Modules
Requires-Dist: click
Requires-Dist: odoo-rpc-client
